xsrp/__init__.py
xsrp/calibrate.py
xsrp/grid_search.py
xsrp/grids.py
xsrp/gui.py
xsrp/multi_source_srp.py
xsrp/spatial_mappers.py
xsrp/srp_mappers.py
xsrp/streaming.py
xsrp/tracking.py
xsrp/xsrp.py
xsrp/signal_features/__init__.py
xsrp/signal_features/cross_correlation.py
xsrp/signal_features/frequency_weighting.py
xsrp/signal_features/gcc_phat.py
xsrp/signal_features/preprocessing.py
xsrp/visualization/__init__.py
xsrp/visualization/cross_correlation.py
xsrp/visualization/grids.py
xsrp/visualization/polar.py
xsrp/visualization/spatial_mappers.py
xsrp-0.1.1.dist-info/METADATA
xsrp-0.1.1.dist-info/WHEEL
xsrp-0.1.1.dist-info/entry_points.txt
xsrp-0.1.1.dist-info/RECORD
