Metadata-Version: 2.4
Name: xsrp
Version: 0.1.1
Summary: eXtensible Steered Response Power for Sound Source Localization
Author: XSRP Contributors
License: MIT
Keywords: audio-processing,direction-of-arrival,doa,microphone-array,signal-processing,sound-source-localization,srp,steered-response-power
Classifier: Development Status :: 4 - Beta
Classifier: Intended Audience :: Developers
Classifier: Intended Audience :: Science/Research
Classifier: License :: OSI Approved :: MIT License
Classifier: Programming Language :: Python :: 3
Classifier: Programming Language :: Python :: 3.9
Classifier: Programming Language :: Python :: 3.10
Classifier: Programming Language :: Python :: 3.11
Classifier: Programming Language :: Python :: 3.12
Classifier: Topic :: Multimedia :: Sound/Audio
Classifier: Topic :: Scientific/Engineering
Requires-Python: >=3.9
Requires-Dist: numpy>=1.25.0
Requires-Dist: scipy>=1.10.0
Provides-Extra: gui
Requires-Dist: h5py>=3.8.0; extra == 'gui'
Requires-Dist: matplotlib>=3.7.0; extra == 'gui'
Requires-Dist: pyaudio>=0.2.11; extra == 'gui'
Requires-Dist: pyqt5>=5.15.0; extra == 'gui'
Requires-Dist: pyyaml>=6.0; extra == 'gui'
